sentient/__init__.py
sentient/decorators.py
sentient_cli/__init__.py
sentient_cli/auth.py
sentient_cli/config.py
sentient_cli/detection.py
sentient_cli/main.py
sentient_cli/commands/__init__.py
sentient_cli/commands/auth.py
sentient_cli/commands/common.py
sentient_cli/commands/delete.py
sentient_cli/commands/init.py
sentient_cli/commands/list.py
sentient_cli/commands/logs.py
sentient_cli/commands/metrics.py
sentient_cli/commands/push.py
sentient_cli/commands/redeploy.py
sentient_cli-0.1.0a1.dist-info/METADATA
sentient_cli-0.1.0a1.dist-info/WHEEL
sentient_cli-0.1.0a1.dist-info/entry_points.txt
sentient_cli-0.1.0a1.dist-info/top_level.txt
sentient_cli-0.1.0a1.dist-info/RECORD
